{
    "levels": [
        {
            "level": "hsc",
            "paths": [
                "science",
                "commerce",
                "arts"
            ]
        },
        {
            "level": "ssc",
            "paths": [
                "science",
                "commerce",
                "arts"
            ]
        },
        {
            "level": "class_8",
            "paths": [
                "general"
            ]
        },
        {
            "level": "class_7",
            "paths": [
                "general"
            ]
        },
        {
            "level": "class_6",
            "paths": [
                "general"
            ]
        },
        {
            "level": "job_exams",
            "paths": [
                "bcs",
                "ssc"
            ]
        }
    ]
}