{
  "path": "courses/hsc_science/course_page_data.json",
  "courseName": "HSC Science",
  "subjects": [
    {
      "subject": "physics",
      "iconName": {
        "codePoint": 60115,
        "fontFamily": "Remix",
        "fontPackage": "remixicon",
        "matchTextDirection": false
      },
      "chapters": [
        {
          "chapter": "vectors",
          "iconName": {
            "codePoint": 61797,
            "fontFamily": "Remix",
            "fontPackage": "remixicon",
            "matchTextDirection": false
          }
        }
      ],
      "initiallyExpanded": false
    },
    {
      "subject": "math",
      "iconName": {
        "codePoint": 60318,
        "fontFamily": "Remix",
        "fontPackage": "remixicon",
        "matchTextDirection": false
      },
      "chapters": [
        {
          "chapter": "graphs",
          "iconName": {
            "codePoint": 61425,
            "fontFamily": "Remix",
            "fontPackage": "remixicon",
            "matchTextDirection": false
          }
        }
      ],
      "initiallyExpanded": false
    },
    {
      "subject": "chemistry",
      "iconName": {
        "codePoint": 60115,
        "fontFamily": "Remix",
        "fontPackage": "remixicon",
        "matchTextDirection": false
      },
      "chapters": [
        {
          "chapter": "molecular_visualization",
          "iconName": {
            "codePoint": 61670,
            "fontFamily": "Remix",
            "fontPackage": "remixicon",
            "matchTextDirection": false
          }
        },
        {
          "chapter": "atomic_structure",
          "iconName": {
            "codePoint": 61671,
            "fontFamily": "Remix",
            "fontPackage": "remixicon",
            "matchTextDirection": false
          }
        },
        {
          "chapter": "chemical_bonding",
          "iconName": {
            "codePoint": 61672,
            "fontFamily": "Remix",
            "fontPackage": "remixicon",
            "matchTextDirection": false
          }
        },
        {
          "chapter": "periodic_table",
          "iconName": {
            "codePoint": 61673,
            "fontFamily": "Remix",
            "fontPackage": "remixicon",
            "matchTextDirection": false
          }
        },
        {
          "chapter": "acids_and_bases",
          "iconName": {
            "codePoint": 61674,
            "fontFamily": "Remix",
            "fontPackage": "remixicon",
            "matchTextDirection": false
          }
        },
        {
          "chapter": "organic_chemistry",
          "iconName": {
            "codePoint": 61675,
            "fontFamily": "Remix",
            "fontPackage": "remixicon",
            "matchTextDirection": false
          }
        }
      ],
      "initiallyExpanded": false
    }
  ]
}